aib_custom_logger_tst/__init__.py
aib_custom_logger_tst/aib_custom_logger.py
aib_custom_logger_tst-1.3.0.dist-info/LICENSE
aib_custom_logger_tst-1.3.0.dist-info/METADATA
aib_custom_logger_tst-1.3.0.dist-info/WHEEL
aib_custom_logger_tst-1.3.0.dist-info/top_level.txt
aib_custom_logger_tst-1.3.0.dist-info/RECORD
