Metadata-Version: 2.1
Name: aib-custom-logger-tst
Version: 1.3.0
Summary: A small example package
Author-email: Shams Sherif <shamsheg@gmail.com>
Project-URL: Homepage, https://github.com/pypa/sampleproject
Project-URL: Bug Tracker, https://github.com/pypa/sampleproject/issues
Classifier: Programming Language :: Python :: 3
Classifier: License :: OSI Approved :: MIT License
Classifier: Operating System :: OS Independent
Requires-Python: >=3.7
License-File: LICENSE
Requires-Dist: google-cloud-logging
